scrapspyder/__init__.py
scrapspyder/scraper.py
scrapspyder-0.1.0.dist-info/METADATA
scrapspyder-0.1.0.dist-info/WHEEL
scrapspyder-0.1.0.dist-info/top_level.txt
scrapspyder-0.1.0.dist-info/RECORD
