Metadata-Version: 2.1
Name: scrapspyder
Version: 0.1.0
Summary: ScrapSpyder: Simple websites scraping package
Home-page: https://github.com/aliwimo/scrapspyder
Author: Mohamed Aliwi
Author-email: aliwimo@gmail.com
License: MIT License
Keywords: scraper,scrap,website scraper,downloader
Classifier: Development Status :: 4 - Beta
Classifier: Intended Audience :: Developers
Classifier: Intended Audience :: Science/Research
Classifier: License :: OSI Approved :: MIT License
Classifier: Operating System :: MacOS
Classifier: Operating System :: Microsoft :: Windows
Classifier: Operating System :: Unix
Classifier: Programming Language :: Python :: 3
Classifier: Topic :: Software Development :: Libraries :: Python Modules
Classifier: Topic :: Utilities
Requires-Dist: requests
Requires-Dist: beautifulsoup4
